MANIFEST.in
Makefile
VERSION
setup.cfg
setup.py
test-requires.txt
charm_benchmark.egg-info/PKG-INFO
charm_benchmark.egg-info/SOURCES.txt
charm_benchmark.egg-info/dependency_links.txt
charm_benchmark.egg-info/pbr.json
charm_benchmark.egg-info/requires.txt
charm_benchmark.egg-info/top_level.txt
charmbenchmark/__init__.py
charmbenchmark/cli/__init__.py
charmbenchmark/cli/actions.py
charmbenchmark/cli/composite.py
charmbenchmark/cli/data.py
charmbenchmark/cli/finish.py
charmbenchmark/cli/meta.py
charmbenchmark/cli/raw.py
charmbenchmark/cli/start.py