Metadata-Version: 1.0
Name: charm-benchmark
Version: 1.1.4
Summary: Library to aid in the creation of benchmark actions in Juju
Home-page: https://github.com/juju-solutions/charm-benchmark
Author: UNKNOWN
Author-email: UNKNOWN
License: UNKNOWN
Platform: UNKNOWN
